_stasm.cpython-37m-darwin.so
stasm/__init__.py
stasm/data/README.txt
stasm/data/haarcascade_frontalface_alt2.xml
stasm/data/haarcascade_mcs_lefteye.xml
stasm/data/haarcascade_mcs_righteye.xml
stasm/data/testface.jpg
stasm-2.0.2.data/headers/asm.h
stasm-2.0.2.data/headers/atface.h
stasm-2.0.2.data/headers/basedesc.h
stasm-2.0.2.data/headers/classicdesc.h
stasm-2.0.2.data/headers/convshape.h
stasm-2.0.2.data/headers/err.h
stasm-2.0.2.data/headers/eyedet.h
stasm-2.0.2.data/headers/eyedist.h
stasm-2.0.2.data/headers/facedet.h
stasm-2.0.2.data/headers/faceroi.h
stasm-2.0.2.data/headers/hat.h
stasm-2.0.2.data/headers/hatdesc.h
stasm-2.0.2.data/headers/initasm.h
stasm-2.0.2.data/headers/landmarks.h
stasm-2.0.2.data/headers/landtab_muct77.h
stasm-2.0.2.data/headers/misc.h
stasm-2.0.2.data/headers/pinstart.h
stasm-2.0.2.data/headers/print.h
stasm-2.0.2.data/headers/shape17.h
stasm-2.0.2.data/headers/shapehacks.h
stasm-2.0.2.data/headers/shapemod.h
stasm-2.0.2.data/headers/startshape.h
stasm-2.0.2.data/headers/stasm.h
stasm-2.0.2.data/headers/stasm_landmarks.h
stasm-2.0.2.data/headers/stasm_lib.h
stasm-2.0.2.data/headers/stasm_lib_ext.h
stasm-2.0.2.data/headers/yaw00.mh
stasm-2.0.2.data/headers/yaw00_lev0_p00_classic.mh
stasm-2.0.2.data/headers/yaw00_lev0_p01_classic.mh
stasm-2.0.2.data/headers/yaw00_lev0_p02_classic.mh
stasm-2.0.2.data/headers/yaw00_lev0_p03_classic.mh
stasm-2.0.2.data/headers/yaw00_lev0_p04_classic.mh
stasm-2.0.2.data/headers/yaw00_lev0_p05_classic.mh
stasm-2.0.2.data/headers/yaw00_lev0_p06_classic.mh
stasm-2.0.2.data/headers/yaw00_lev0_p07_classic.mh
stasm-2.0.2.data/headers/yaw00_lev0_p08_classic.mh
stasm-2.0.2.data/headers/yaw00_lev0_p09_classic.mh
stasm-2.0.2.data/headers/yaw00_lev0_p10_classic.mh
stasm-2.0.2.data/headers/yaw00_lev0_p11_classic.mh
stasm-2.0.2.data/headers/yaw00_lev0_p12_classic.mh
stasm-2.0.2.data/headers/yaw00_lev0_p13_classic.mh
stasm-2.0.2.data/headers/yaw00_lev0_p14_classic.mh
stasm-2.0.2.data/headers/yaw00_lev0_p15_classic.mh
stasm-2.0.2.dist-info/LICENSE.txt
stasm-2.0.2.dist-info/METADATA
stasm-2.0.2.dist-info/WHEEL
stasm-2.0.2.dist-info/top_level.txt
stasm-2.0.2.dist-info/RECORD
